aiot/__init__.py
aiot/app.py
aiot/board.py
aiot/boardcontrol_linux.py
aiot/boardcontrol_win.py
aiot/bootrom.py
aiot/bootrom_log_parser.py
aiot/config.py
aiot/efuse.py
aiot/fastboot.py
aiot/flash.py
aiot/flash_daemon.py
aiot/flash_worker.py
aiot/flashtool.py
aiot/ftdi.py
aiot/ftdi_win.py
aiot/multi_download_cli.py
aiot/rpmb.py
aiot/ubootenv.py
aiot/version.py
aiot/image/__init__.py
aiot/image/android.py
aiot/image/bootfirmware.py
aiot/image/raw.py
aiot/image/ubuntu.py
aiot/image/yocto.py
genio_tools-1.7.0.dist-info/licenses/LICENSE
genio_tools-1.7.0.dist-info/METADATA
genio_tools-1.7.0.dist-info/WHEEL
genio_tools-1.7.0.dist-info/entry_points.txt
genio_tools-1.7.0.dist-info/top_level.txt
genio_tools-1.7.0.dist-info/RECORD
