Metadata-Version: 2.4
Name: genio-tools
Version: 1.7.0
Summary: Tools for flashing boards using MediaTek Genio SoCs
Home-page: https://gitlab.com/mediatek/aiot/bsp/genio-tools
Author: Fabien Parent
Maintainer: Pablo Sun
Maintainer-email: Pablo Sun <pablo.sun@mediatek.com>
License: Copyright (c) 2020 BayLibre, SAS
Project-URL: Homepage, https://mediatek.gitlab.io/aiot/doc/aiot-dev-guide/master/tools/genio-tools.html
Classifier: License :: OSI Approved :: MIT License
Classifier: Operating System :: OS Independent
Classifier: Programming Language :: Python :: 3
Requires-Python: >=3.9
License-File: LICENSE
Requires-Dist: genio-bootrom>=1.2.1
Requires-Dist: windows-curses; platform_system == "Windows"
Requires-Dist: keyboard
Requires-Dist: gpiod==1.4.0
Requires-Dist: oyaml
Requires-Dist: packaging
Requires-Dist: psutil
Requires-Dist: pyftdi
Requires-Dist: pyusb
Requires-Dist: pyudev; platform_system == "Linux"
Requires-Dist: ftd2xx; platform_system == "Windows"
Requires-Dist: fastboot-log-parser
Dynamic: home-page
Dynamic: license-file
Dynamic: maintainer
Dynamic: requires-dist
Dynamic: requires-python
